{"version":1,"resource":"file:///home/zmrocze/mlabs/bot-plutus-interface.git/master/src/BotPlutusInterface/Contract.hs","entries":[{"id":"SEwp.hs","timestamp":1663174170055},{"id":"roXu.hs","timestamp":1664388174492},{"id":"Gw3Y.hs","source":"import qualified Wallet.API as WAPI","timestamp":1664388189149},{"id":"mYIr.hs","timestamp":1664388206759},{"id":"LGmQ.hs","timestamp":1664388222390},{"id":"kGwN.hs","timestamp":1664455620646},{"id":"KnrX.hs","timestamp":1664455635480},{"id":"l9eW.hs","timestamp":1664456756631},{"id":"3tH7.hs","timestamp":1664457032085},{"id":"bO72.hs","timestamp":1664457045325},{"id":"jwLZ.hs","timestamp":1664457055688},{"id":"gxK8.hs","timestamp":1664457077808},{"id":"hovM.hs","timestamp":1664457126915},{"id":"Qm65.hs","timestamp":1664457171486},{"id":"uASp.hs","timestamp":1664457183943},{"id":"cZrS.hs","timestamp":1664457203700},{"id":"FRUr.hs","source":"import qualified Data.Text as T","timestamp":1664457208513},{"id":"w8Aq.hs","timestamp":1664474648644},{"id":"yFUl.hs","timestamp":1664478036099}]}