{"version":1,"resource":"file:///home/zmrocze/mlabs/plutip/CHANGELOG.md","entries":[{"id":"NbUl.md","timestamp":1654706705430},{"id":"3Zha.md","timestamp":1654706852409},{"id":"PXfE.md","timestamp":1654706884186},{"id":"vhKl.md","timestamp":1654706967777},{"id":"saYf.md","timestamp":1654706994191},{"id":"N7Dk.md","timestamp":1654707090189},{"id":"EA5G.md","timestamp":1654707120579},{"id":"8rui.md","timestamp":1654707154250},{"id":"emcC.md","timestamp":1654707236171},{"id":"j5xQ.md","timestamp":1654707281565},{"id":"a6RQ.md","timestamp":1654707316222},{"id":"CGsa.md","timestamp":1654772143914}]}