{"version":1,"resource":"file:///home/zmrocze/mlabs/plutip/staking-keys/src/Test/Plutip/Contract/Init.hs","entries":[{"id":"hhu3.hs","timestamp":1663099170786},{"id":"jOM0.hs","timestamp":1663331281749},{"id":"7o1C.hs","timestamp":1663331294539},{"id":"tOTk.hs","timestamp":1663331306929},{"id":"2XKH.hs","timestamp":1663331339916},{"id":"gocL.hs","timestamp":1663333657733},{"id":"GCYo.hs","timestamp":1663333670940},{"id":"ojHb.hs","timestamp":1663333718190},{"id":"8JR0.hs","timestamp":1663333780451},{"id":"R5Qq.hs","timestamp":1663333852315},{"id":"4vjX.hs","timestamp":1663333917699},{"id":"ocsJ.hs","timestamp":1663333933719},{"id":"0vk0.hs","timestamp":1663333985287},{"id":"1wP4.hs","timestamp":1663334031054},{"id":"Ufgv.hs","source":"Add TestWallet(hasStakeKeys) to the import list of Test.Plutip.Contract.Types","timestamp":1663334037221},{"id":"Ucz5.hs","timestamp":1663334067488},{"id":"Iq2A.hs","timestamp":1663334078878},{"id":"dUBQ.hs","timestamp":1663334092555},{"id":"XD7e.hs","timestamp":1663334238363},{"id":"iU0S.hs","timestamp":1663334253796},{"id":"AN70.hs","timestamp":1663334265483},{"id":"8ruE.hs","timestamp":1663334291150},{"id":"PfPf.hs","timestamp":1663334306330},{"id":"tdvP.hs","timestamp":1663434724862},{"id":"hiMS.hs","timestamp":1663694678074},{"id":"5PtR.hs","timestamp":1663699249530},{"id":"9UIY.hs","timestamp":1663699302193},{"id":"cOCG.hs","timestamp":1663703857502},{"id":"zQRB.hs","timestamp":1663785470968},{"id":"e4iJ.hs","timestamp":1663877615706},{"id":"ZveB.hs","timestamp":1663877639062},{"id":"bE6n.hs","timestamp":1663877693574},{"id":"sgeO.hs","timestamp":1663877713705},{"id":"0ylb.hs","timestamp":1663877737005},{"id":"g2O5.hs","timestamp":1663877756813},{"id":"zo9r.hs","timestamp":1663877804154},{"id":"WWhJ.hs","timestamp":1663877904894},{"id":"7rnE.hs","timestamp":1663877933430},{"id":"r9GA.hs","timestamp":1663933574551},{"id":"Qs1w.hs","timestamp":1663939824789},{"id":"gH3D.hs","source":"Add WalletTag to the import list of Test.Plutip.Internal.BotPlutusInterface.Types","timestamp":1663939830156},{"id":"IH4h.hs","timestamp":1663939846856},{"id":"tSnD.hs","timestamp":1663939893623},{"id":"A62C.hs","timestamp":1663939914804},{"id":"NWe0.hs","source":"Add TestWallet'(TestWallet') to the import list of Test.Plutip.Internal.BotPlutusInterface.Types","timestamp":1663939927721},{"id":"HUMm.hs","timestamp":1663950171563},{"id":"0Aqe.hs","timestamp":1663950193077},{"id":"kJzx.hs","timestamp":1663950204093},{"id":"S9KF.hs","timestamp":1664204063940}]}