{"version":1,"resource":"file:///home/zmrocze/code/haskell/standard-chartered-interview/interview/app/Main.hs","entries":[{"id":"FrWv.hs","timestamp":1671720146206},{"id":"pFAD.hs","timestamp":1671720168048},{"id":"KeQn.hs","timestamp":1671720194917},{"id":"jrCo.hs","timestamp":1671720212043},{"id":"aVxZ.hs","timestamp":1671720230066},{"id":"dJde.hs","timestamp":1671720251871},{"id":"iA1N.hs","timestamp":1671720280207},{"id":"PkCb.hs","timestamp":1671720643020},{"id":"XmOp.hs","timestamp":1671720674955},{"id":"OEBG.hs","timestamp":1671720772011},{"id":"OlV3.hs","timestamp":1671720882056},{"id":"Lp0V.hs","timestamp":1671720943539},{"id":"brEN.hs","timestamp":1671720968416},{"id":"U6m2.hs","timestamp":1671721116355},{"id":"J9fP.hs","source":"undoRedo.source","timestamp":1671721173535},{"id":"AObH.hs","timestamp":1671721203378},{"id":"yB3w.hs","timestamp":1671721229464},{"id":"jLg6.hs","timestamp":1671721637546},{"id":"OV0F.hs","timestamp":1671721662446},{"id":"17BE.hs","timestamp":1671721672933},{"id":"fax0.hs","timestamp":1671721690840},{"id":"G7X8.hs","timestamp":1671721704504},{"id":"QgAG.hs","timestamp":1671721738114},{"id":"a3vD.hs","timestamp":1671721775195},{"id":"9lqZ.hs","timestamp":1671721791601},{"id":"YSm3.hs","timestamp":1671721820258},{"id":"j0oM.hs","timestamp":1671721833372},{"id":"Fgn8.hs","timestamp":1671722224936},{"id":"uFZz.hs","timestamp":1671722340162},{"id":"FXbn.hs","timestamp":1671722385059},{"id":"cuXh.hs","timestamp":1671722398279},{"id":"OVfp.hs","timestamp":1671722690097},{"id":"zcLe.hs","source":"undoRedo.source","timestamp":1671722693317},{"id":"atSj.hs","timestamp":1671722780730},{"id":"FBS3.hs","timestamp":1671722804913},{"id":"OAgj.hs","timestamp":1671722822913},{"id":"cSLc.hs","timestamp":1671722851519},{"id":"19bc.hs","timestamp":1671722862169},{"id":"mDtu.hs","timestamp":1671722896959},{"id":"7sXV.hs","timestamp":1671722911115},{"id":"8Q6s.hs","timestamp":1671722968165},{"id":"c3Qm.hs","timestamp":1671722987951},{"id":"doQi.hs","timestamp":1671723002511},{"id":"OCIT.hs","timestamp":1671723025338},{"id":"tATp.hs","timestamp":1671723047457},{"id":"yymB.hs","timestamp":1671723062524},{"id":"AQaP.hs","timestamp":1671723102213},{"id":"8OIf.hs","timestamp":1671723118450},{"id":"SOIX.hs","timestamp":1671723133060},{"id":"ByaK.hs","timestamp":1671723211709}]}